binaryen.py
pybinaryen-1.124.dist-info/licenses/LICENSE
pybinaryen-1.124.dist-info/METADATA
pybinaryen-1.124.dist-info/WHEEL
pybinaryen-1.124.dist-info/top_level.txt
pybinaryen-1.124.dist-info/RECORD
