Metadata-Version: 2.4
Name: pybinaryen
Version: 1.124
Summary: python bindings for the binaryen webassembly library
Home-page: https://github.com/irmen/binaryen-interfaces/tree/master/pybinaryen
Author: Irmen de Jong
Author-email: irmen@razorvine.net
License: MIT
Keywords: webassembly
Classifier: License :: OSI Approved :: MIT License
Classifier: Development Status :: 4 - Beta
Classifier: Programming Language :: C
Classifier: Programming Language :: Python
Classifier: Programming Language :: Python :: 3
License-File: LICENSE
Requires-Dist: cffi>=1.3.0
Dynamic: license-file
Dynamic: requires-dist
